cocheck/__init__.py
cocheck/main.py
cocheck/cocheck/__init__.py
cocheck-0.1.2.dist-info/METADATA
cocheck-0.1.2.dist-info/WHEEL
cocheck-0.1.2.dist-info/top_level.txt
cocheck-0.1.2.dist-info/RECORD
